pinata.py
Pinata-0.0.1.dist-info/LICENCE
Pinata-0.0.1.dist-info/METADATA
Pinata-0.0.1.dist-info/WHEEL
Pinata-0.0.1.dist-info/top_level.txt
Pinata-0.0.1.dist-info/RECORD
