Metadata-Version: 2.1
Name: Pinata
Version: 0.0.1
Summary: Unofficial library for accessing Pinata's IPFS APIs
Home-page: https://github.com/GrishonNganga/Pinata-Python
Author: Grishon Ng'ang'a
Author-email: grishon.nganga01@gmail.com
License: UNKNOWN
Platform: UNKNOWN
Classifier: Programming Language :: Python :: 3
Classifier: License :: OSI Approved :: MIT License
Classifier: Operating System :: OS Independent
Requires-Dist: requests (>=2.0)
Provides-Extra: dev
Requires-Dist: pytest (==7.0) ; extra == 'dev'
